redc-0.1.13.dist-info/RECORD
redc-0.1.13.dist-info/WHEEL
redc-0.1.13.dist-info/METADATA
redc-0.1.13.dist-info/licenses/LICENSE
redc/callback.py
redc/_version.py
redc/codes.py
redc/client.py
redc/__init__.py
redc/response.py
redc/callbacks.py
redc/redc_ext.cpython-313t-darwin.so
redc/ext/redc.h
redc/ext/redc.cpp
redc/ext/utils/curl_utils.h
redc/ext/utils/memoryview.h
redc/ext/utils/concurrentqueue.h
redc/utils/__init__.py
redc/utils/_io_utils.py
redc/utils/json_encoder.py
redc/utils/http.py
redc/utils/headers.py
redc/exceptions/__init__.py
redc/.dylibs/libngtcp2_crypto_ossl.0.dylib
redc/.dylibs/libbrotlicommon.1.2.0.dylib
redc/.dylibs/libbrotlidec.1.2.0.dylib
redc/.dylibs/libidn2.0.dylib
redc/.dylibs/libssl.3.dylib
redc/.dylibs/libngtcp2.16.dylib
redc/.dylibs/libcares.2.dylib
redc/.dylibs/libcrypto.3.dylib
redc/.dylibs/libz.1.3.1.dylib
redc/.dylibs/libnghttp2.14.dylib
redc/.dylibs/libpsl.5.dylib
redc/.dylibs/libcurl.4.dylib
redc/.dylibs/libnghttp3.9.dylib
redc/.dylibs/libunistring.5.dylib
redc/.dylibs/libzstd.1.5.7.dylib
