Metadata-Version: 2.2
Name: redc
Version: 0.1.13
Summary: RedC is a high-performance, asynchronous HTTP client library for Python, built on top of the powerful curl library
Keywords: asyncio,http,client,http-client,curl,libcurl
Author-Email: AYMEN Mohammed <let.me.code.safe@gmail.com>
License: MIT
Project-URL: Source, https://github.com/AYMENJD/redc
Project-URL: Tracker, https://github.com/AYMENJD/redc/issues
Requires-Python: >=3.9
Requires-Dist: trustifi
